[
    {
        "text": "Что разбудило Спящую Красавицу?",
        "answers": [
            "Поцелуй принца",
            "Шумные соседи",
            "Будильник",
            "Телефон"
        ],
        "points": 1,
        "difficulty": {
            "__difficulty": 0
        },
        "correct_answer": 0
    },
    {
        "text": "Какой обитатель водной стихии заслужил репутацию отшельника?",
        "answers": [
            "Рак",
            "Бычок",
            "Дельфин",
            "Медуза"
        ],
        "points": 1,
        "difficulty": {
            "__difficulty": 0
        },
        "correct_answer": 0
    },
    {
        "text": "Какого падежа в русском языке не существует?",
        "answers": [
            "Подложный",
            "Дательный",
            "Творительный",
            "Винительный"
        ],
        "points": 1,
        "difficulty": {
            "__difficulty": 0
        },
        "correct_answer": 0
    },
    {
        "text": "Что используют для поджаривания ломтиков хлеба?",
        "answers": [
            "Тостер",
            "Постер",
            "Винчестер",
            "Компостер"
        ],
        "points": 1,
        "difficulty": {
            "__difficulty": 0
        },
        "correct_answer": 0
    },
    {
        "text": "Как называется повесть Астрид Линдгрен: \"Малыш и...\"?",
        "answers": [
            "..Карлсон",
            "..Иван",
            "..собака",
            "..Взрослый"
        ],
        "points": 1,
        "difficulty": {
            "__difficulty": 0
        },
        "correct_answer": 0
    },
    {
        "text": "Где проходила Олимпиада, на которой бросок А. Белова вывел баскетбольную команду СССР в чемпионы?",
        "answers": [
            "Мюнхен",
            "Рим",
            "Монреаль",
            "Мехико"
        ],
        "points": 2,
        "difficulty": {
            "__difficulty": 1
        },
        "correct_answer": 0
    },
    {
        "text": "Какой персонаж оперы Глинки \"Руслан и Людмила\" не поёт?",
        "answers": [
            "Черномор",
            "Ратмир",
            "Наина",
            "Финн"
        ],
        "points": 2,
        "difficulty": {
            "__difficulty": 1
        },
        "correct_answer": 0
    },
    {
        "text": "Сколько корон на Государственном гербе РФ?",
        "answers": [
            "Три",
            "Одна",
            "Две",
            "Пять"
        ],
        "points": 2,
        "difficulty": {
            "__difficulty": 1
        },
        "correct_answer": 0
    },
    {
        "text": "На территории какой страны был открыт золотоносный район Клондайк?",
        "answers": [
            "Канада",
            "США",
            "Мексика",
            "Венесуэла"
        ],
        "points": 2,
        "difficulty": {
            "__difficulty": 1
        },
        "correct_answer": 0
    },
    {
        "text": "Месторасположение какой из этих станций в Антарктиде совпадает с полюсом холода?",
        "answers": [
            "\"Восток\"",
            "\"Пионерская\"",
            "\"Молодёжная\"",
            "\"Мирный\""
        ],
        "points": 2,
        "difficulty": {
            "__difficulty": 1
        },
        "correct_answer": 0
    },
    {
        "text": "В какой из этих столиц бывших союзных республик раньше появилось метро?",
        "answers": [
            "Тбилиси",
            "Минск",
            "Ереван",
            "Баку"
        ],
        "points": 3,
        "difficulty": {
            "__difficulty": 2
        },
        "correct_answer": 0
    },
    {
        "text": "Реки с каким названием нет на территории России?",
        "answers": [
            "Спина",
            "Шея",
            "Уста",
            "Палец"
        ],
        "points": 3,
        "difficulty": {
            "__difficulty": 2
        },
        "correct_answer": 0
    },
    {
        "text": "Какой химический элемент назван в честь злого подземного гнома?",
        "answers": [
            "Кобальт",
            "Берилий",
            "Теллур",
            "Гафний"
        ],
        "points": 3,
        "difficulty": {
            "__difficulty": 2
        },
        "correct_answer": 0
    },
    {
        "text": "В честь какого растения область Фриули-Венеция-Джулия в Италии ежегодно проводит трёхмесячный фестиваль?",
        "answers": [
            "Спаржа",
            "Лук",
            "Фасоль",
            "Артишок"
        ],
        "points": 3,
        "difficulty": {
            "__difficulty": 2
        },
        "correct_answer": 0
    },
    {
        "text": "Кто из перечисленных был пажом во времена Екатерины II?",
        "answers": [
            "А.Н. Радищев",
            "Н.М. Карамзин",
            "Д.И. Фонвизин",
            "Г.Р. Державин"
        ],
        "points": 3,
        "difficulty": {
            "__difficulty": 2
        },
        "correct_answer": 0
    },
    {
        "text": "Какого падежа в русском языке не существует?",
        "answers": [
            "Подложный",
            "Дательный",
            "Творительный",
            "Винительный"
        ],
        "points": 1,
        "difficulty": {
            "__difficulty": 0
        },
        "correct_answer": 0
    },
    {
        "text": "Как называется повесть Астрид Линдгрен: \"Малыш и...\"?",
        "answers": [
            "..Карлсон",
            "..Иван",
            "..собака",
            "..Взрослый"
        ],
        "points": 1,
        "difficulty": {
            "__difficulty": 0
        },
        "correct_answer": 0
    },
    {
        "text": "Какой обитатель водной стихии заслужил репутацию отшельника?",
        "answers": [
            "Рак",
            "Бычок",
            "Дельфин",
            "Медуза"
        ],
        "points": 1,
        "difficulty": {
            "__difficulty": 0
        },
        "correct_answer": 0
    },
    {
        "text": "Что разбудило Спящую Красавицу?",
        "answers": [
            "Поцелуй принца",
            "Шумные соседи",
            "Будильник",
            "Телефон"
        ],
        "points": 1,
        "difficulty": {
            "__difficulty": 0
        },
        "correct_answer": 0
    },
    {
        "text": "Что используют для поджаривания ломтиков хлеба?",
        "answers": [
            "Тостер",
            "Постер",
            "Винчестер",
            "Компостер"
        ],
        "points": 1,
        "difficulty": {
            "__difficulty": 0
        },
        "correct_answer": 0
    },
    {
        "text": "Где проходила Олимпиада, на которой бросок А. Белова вывел баскетбольную команду СССР в чемпионы?",
        "answers": [
            "Мюнхен",
            "Рим",
            "Монреаль",
            "Мехико"
        ],
        "points": 2,
        "difficulty": {
            "__difficulty": 1
        },
        "correct_answer": 0
    },
    {
        "text": "Сколько корон на Государственном гербе РФ?",
        "answers": [
            "Три",
            "Одна",
            "Две",
            "Пять"
        ],
        "points": 2,
        "difficulty": {
            "__difficulty": 1
        },
        "correct_answer": 0
    },
    {
        "text": "Какой персонаж оперы Глинки \"Руслан и Людмила\" не поёт?",
        "answers": [
            "Черномор",
            "Ратмир",
            "Наина",
            "Финн"
        ],
        "points": 2,
        "difficulty": {
            "__difficulty": 1
        },
        "correct_answer": 0
    },
    {
        "text": "На территории какой страны был открыт золотоносный район Клондайк?",
        "answers": [
            "Канада",
            "США",
            "Мексика",
            "Венесуэла"
        ],
        "points": 2,
        "difficulty": {
            "__difficulty": 1
        },
        "correct_answer": 0
    },
    {
        "text": "Месторасположение какой из этих станций в Антарктиде совпадает с полюсом холода?",
        "answers": [
            "\"Восток\"",
            "\"Пионерская\"",
            "\"Молодёжная\"",
            "\"Мирный\""
        ],
        "points": 2,
        "difficulty": {
            "__difficulty": 1
        },
        "correct_answer": 0
    },
    {
        "text": "Реки с каким названием нет на территории России?",
        "answers": [
            "Спина",
            "Шея",
            "Уста",
            "Палец"
        ],
        "points": 3,
        "difficulty": {
            "__difficulty": 2
        },
        "correct_answer": 0
    },
    {
        "text": "В честь какого растения область Фриули-Венеция-Джулия в Италии ежегодно проводит трёхмесячный фестиваль?",
        "answers": [
            "Спаржа",
            "Лук",
            "Фасоль",
            "Артишок"
        ],
        "points": 3,
        "difficulty": {
            "__difficulty": 2
        },
        "correct_answer": 0
    },
    {
        "text": "Какой химический элемент назван в честь злого подземного гнома?",
        "answers": [
            "Кобальт",
            "Берилий",
            "Теллур",
            "Гафний"
        ],
        "points": 3,
        "difficulty": {
            "__difficulty": 2
        },
        "correct_answer": 0
    },
    {
        "text": "В какой из этих столиц бывших союзных республик раньше появилось метро?",
        "answers": [
            "Тбилиси",
            "Минск",
            "Ереван",
            "Баку"
        ],
        "points": 3,
        "difficulty": {
            "__difficulty": 2
        },
        "correct_answer": 0
    },
    {
        "text": "Кто из перечисленных был пажом во времена Екатерины II?",
        "answers": [
            "А.Н. Радищев",
            "Н.М. Карамзин",
            "Д.И. Фонвизин",
            "Г.Р. Державин"
        ],
        "points": 3,
        "difficulty": {
            "__difficulty": 2
        },
        "correct_answer": 0
    },
    {
        "text": "Какого падежа в русском языке не существует?",
        "answers": [
            "Подложный",
            "Дательный",
            "Творительный",
            "Винительный"
        ],
        "points": 1,
        "difficulty": {
            "__difficulty": 0
        },
        "correct_answer": 0
    },
    {
        "text": "Какой обитатель водной стихии заслужил репутацию отшельника?",
        "answers": [
            "Рак",
            "Бычок",
            "Дельфин",
            "Медуза"
        ],
        "points": 1,
        "difficulty": {
            "__difficulty": 0
        },
        "correct_answer": 0
    },
    {
        "text": "Как называется повесть Астрид Линдгрен: \"Малыш и...\"?",
        "answers": [
            "..Карлсон",
            "..Иван",
            "..собака",
            "..Взрослый"
        ],
        "points": 1,
        "difficulty": {
            "__difficulty": 0
        },
        "correct_answer": 0
    },
    {
        "text": "Что разбудило Спящую Красавицу?",
        "answers": [
            "Поцелуй принца",
            "Шумные соседи",
            "Будильник",
            "Телефон"
        ],
        "points": 1,
        "difficulty": {
            "__difficulty": 0
        },
        "correct_answer": 0
    },
    {
        "text": "Что используют для поджаривания ломтиков хлеба?",
        "answers": [
            "Тостер",
            "Постер",
            "Винчестер",
            "Компостер"
        ],
        "points": 1,
        "difficulty": {
            "__difficulty": 0
        },
        "correct_answer": 0
    },
    {
        "text": "Сколько корон на Государственном гербе РФ?",
        "answers": [
            "Три",
            "Одна",
            "Две",
            "Пять"
        ],
        "points": 2,
        "difficulty": {
            "__difficulty": 1
        },
        "correct_answer": 0
    },
    {
        "text": "Где проходила Олимпиада, на которой бросок А. Белова вывел баскетбольную команду СССР в чемпионы?",
        "answers": [
            "Мюнхен",
            "Рим",
            "Монреаль",
            "Мехико"
        ],
        "points": 2,
        "difficulty": {
            "__difficulty": 1
        },
        "correct_answer": 0
    },
    {
        "text": "На территории какой страны был открыт золотоносный район Клондайк?",
        "answers": [
            "Канада",
            "США",
            "Мексика",
            "Венесуэла"
        ],
        "points": 2,
        "difficulty": {
            "__difficulty": 1
        },
        "correct_answer": 0
    },
    {
        "text": "Какой персонаж оперы Глинки \"Руслан и Людмила\" не поёт?",
        "answers": [
            "Черномор",
            "Ратмир",
            "Наина",
            "Финн"
        ],
        "points": 2,
        "difficulty": {
            "__difficulty": 1
        },
        "correct_answer": 0
    },
    {
        "text": "Месторасположение какой из этих станций в Антарктиде совпадает с полюсом холода?",
        "answers": [
            "\"Восток\"",
            "\"Пионерская\"",
            "\"Молодёжная\"",
            "\"Мирный\""
        ],
        "points": 2,
        "difficulty": {
            "__difficulty": 1
        },
        "correct_answer": 0
    },
    {
        "text": "Какой химический элемент назван в честь злого подземного гнома?",
        "answers": [
            "Кобальт",
            "Берилий",
            "Теллур",
            "Гафний"
        ],
        "points": 3,
        "difficulty": {
            "__difficulty": 2
        },
        "correct_answer": 0
    },
    {
        "text": "Реки с каким названием нет на территории России?",
        "answers": [
            "Спина",
            "Шея",
            "Уста",
            "Палец"
        ],
        "points": 3,
        "difficulty": {
            "__difficulty": 2
        },
        "correct_answer": 0
    },
    {
        "text": "Кто из перечисленных был пажом во времена Екатерины II?",
        "answers": [
            "А.Н. Радищев",
            "Н.М. Карамзин",
            "Д.И. Фонвизин",
            "Г.Р. Державин"
        ],
        "points": 3,
        "difficulty": {
            "__difficulty": 2
        },
        "correct_answer": 0
    },
    {
        "text": "В какой из этих столиц бывших союзных республик раньше появилось метро?",
        "answers": [
            "Тбилиси",
            "Минск",
            "Ереван",
            "Баку"
        ],
        "points": 3,
        "difficulty": {
            "__difficulty": 2
        },
        "correct_answer": 0
    },
    {
        "text": "В честь какого растения область Фриули-Венеция-Джулия в Италии ежегодно проводит трёхмесячный фестиваль?",
        "answers": [
            "Спаржа",
            "Лук",
            "Фасоль",
            "Артишок"
        ],
        "points": 3,
        "difficulty": {
            "__difficulty": 2
        },
        "correct_answer": 0
    },
    {
        "text": "Что используют для поджаривания ломтиков хлеба?",
        "answers": [
            "Тостер",
            "Постер",
            "Винчестер",
            "Компостер"
        ],
        "points": 1,
        "difficulty": {
            "__difficulty": 0
        },
        "correct_answer": 0
    },
    {
        "text": "Как называется повесть Астрид Линдгрен: \"Малыш и...\"?",
        "answers": [
            "..Карлсон",
            "..Иван",
            "..собака",
            "..Взрослый"
        ],
        "points": 1,
        "difficulty": {
            "__difficulty": 0
        },
        "correct_answer": 0
    },
    {
        "text": "Какой обитатель водной стихии заслужил репутацию отшельника?",
        "answers": [
            "Рак",
            "Бычок",
            "Дельфин",
            "Медуза"
        ],
        "points": 1,
        "difficulty": {
            "__difficulty": 0
        },
        "correct_answer": 0
    },
    {
        "text": "Какого падежа в русском языке не существует?",
        "answers": [
            "Подложный",
            "Дательный",
            "Творительный",
            "Винительный"
        ],
        "points": 1,
        "difficulty": {
            "__difficulty": 0
        },
        "correct_answer": 0
    },
    {
        "text": "Что разбудило Спящую Красавицу?",
        "answers": [
            "Поцелуй принца",
            "Шумные соседи",
            "Будильник",
            "Телефон"
        ],
        "points": 1,
        "difficulty": {
            "__difficulty": 0
        },
        "correct_answer": 0
    },
    {
        "text": "Где проходила Олимпиада, на которой бросок А. Белова вывел баскетбольную команду СССР в чемпионы?",
        "answers": [
            "Мюнхен",
            "Рим",
            "Монреаль",
            "Мехико"
        ],
        "points": 2,
        "difficulty": {
            "__difficulty": 1
        },
        "correct_answer": 0
    },
    {
        "text": "Сколько корон на Государственном гербе РФ?",
        "answers": [
            "Три",
            "Одна",
            "Две",
            "Пять"
        ],
        "points": 2,
        "difficulty": {
            "__difficulty": 1
        },
        "correct_answer": 0
    },
    {
        "text": "На территории какой страны был открыт золотоносный район Клондайк?",
        "answers": [
            "Канада",
            "США",
            "Мексика",
            "Венесуэла"
        ],
        "points": 2,
        "difficulty": {
            "__difficulty": 1
        },
        "correct_answer": 0
    },
    {
        "text": "Какой персонаж оперы Глинки \"Руслан и Людмила\" не поёт?",
        "answers": [
            "Черномор",
            "Ратмир",
            "Наина",
            "Финн"
        ],
        "points": 2,
        "difficulty": {
            "__difficulty": 1
        },
        "correct_answer": 0
    },
    {
        "text": "Месторасположение какой из этих станций в Антарктиде совпадает с полюсом холода?",
        "answers": [
            "\"Восток\"",
            "\"Пионерская\"",
            "\"Молодёжная\"",
            "\"Мирный\""
        ],
        "points": 2,
        "difficulty": {
            "__difficulty": 1
        },
        "correct_answer": 0
    },
    {
        "text": "Реки с каким названием нет на территории России?",
        "answers": [
            "Спина",
            "Шея",
            "Уста",
            "Палец"
        ],
        "points": 3,
        "difficulty": {
            "__difficulty": 2
        },
        "correct_answer": 0
    },
    {
        "text": "В честь какого растения область Фриули-Венеция-Джулия в Италии ежегодно проводит трёхмесячный фестиваль?",
        "answers": [
            "Спаржа",
            "Лук",
            "Фасоль",
            "Артишок"
        ],
        "points": 3,
        "difficulty": {
            "__difficulty": 2
        },
        "correct_answer": 0
    },
    {
        "text": "Какой химический элемент назван в честь злого подземного гнома?",
        "answers": [
            "Кобальт",
            "Берилий",
            "Теллур",
            "Гафний"
        ],
        "points": 3,
        "difficulty": {
            "__difficulty": 2
        },
        "correct_answer": 0
    },
    {
        "text": "В какой из этих столиц бывших союзных республик раньше появилось метро?",
        "answers": [
            "Тбилиси",
            "Минск",
            "Ереван",
            "Баку"
        ],
        "points": 3,
        "difficulty": {
            "__difficulty": 2
        },
        "correct_answer": 0
    },
    {
        "text": "Кто из перечисленных был пажом во времена Екатерины II?",
        "answers": [
            "А.Н. Радищев",
            "Н.М. Карамзин",
            "Д.И. Фонвизин",
            "Г.Р. Державин"
        ],
        "points": 3,
        "difficulty": {
            "__difficulty": 2
        },
        "correct_answer": 0
    },
    {
        "text": "Какого падежа в русском языке не существует?",
        "answers": [
            "Подложный",
            "Дательный",
            "Творительный",
            "Винительный"
        ],
        "points": 1,
        "difficulty": {
            "__difficulty": 0
        },
        "correct_answer": 0
    },
    {
        "text": "Что разбудило Спящую Красавицу?",
        "answers": [
            "Поцелуй принца",
            "Шумные соседи",
            "Будильник",
            "Телефон"
        ],
        "points": 1,
        "difficulty": {
            "__difficulty": 0
        },
        "correct_answer": 0
    },
    {
        "text": "Какой обитатель водной стихии заслужил репутацию отшельника?",
        "answers": [
            "Рак",
            "Бычок",
            "Дельфин",
            "Медуза"
        ],
        "points": 1,
        "difficulty": {
            "__difficulty": 0
        },
        "correct_answer": 0
    },
    {
        "text": "Как называется повесть Астрид Линдгрен: \"Малыш и...\"?",
        "answers": [
            "..Карлсон",
            "..Иван",
            "..собака",
            "..Взрослый"
        ],
        "points": 1,
        "difficulty": {
            "__difficulty": 0
        },
        "correct_answer": 0
    },
    {
        "text": "Что используют для поджаривания ломтиков хлеба?",
        "answers": [
            "Тостер",
            "Постер",
            "Винчестер",
            "Компостер"
        ],
        "points": 1,
        "difficulty": {
            "__difficulty": 0
        },
        "correct_answer": 0
    },
    {
        "text": "Месторасположение какой из этих станций в Антарктиде совпадает с полюсом холода?",
        "answers": [
            "\"Восток\"",
            "\"Пионерская\"",
            "\"Молодёжная\"",
            "\"Мирный\""
        ],
        "points": 2,
        "difficulty": {
            "__difficulty": 1
        },
        "correct_answer": 0
    },
    {
        "text": "Где проходила Олимпиада, на которой бросок А. Белова вывел баскетбольную команду СССР в чемпионы?",
        "answers": [
            "Мюнхен",
            "Рим",
            "Монреаль",
            "Мехико"
        ],
        "points": 2,
        "difficulty": {
            "__difficulty": 1
        },
        "correct_answer": 0
    },
    {
        "text": "На территории какой страны был открыт золотоносный район Клондайк?",
        "answers": [
            "Канада",
            "США",
            "Мексика",
            "Венесуэла"
        ],
        "points": 2,
        "difficulty": {
            "__difficulty": 1
        },
        "correct_answer": 0
    },
    {
        "text": "Сколько корон на Государственном гербе РФ?",
        "answers": [
            "Три",
            "Одна",
            "Две",
            "Пять"
        ],
        "points": 2,
        "difficulty": {
            "__difficulty": 1
        },
        "correct_answer": 0
    },
    {
        "text": "Какой персонаж оперы Глинки \"Руслан и Людмила\" не поёт?",
        "answers": [
            "Черномор",
            "Ратмир",
            "Наина",
            "Финн"
        ],
        "points": 2,
        "difficulty": {
            "__difficulty": 1
        },
        "correct_answer": 0
    },
    {
        "text": "Реки с каким названием нет на территории России?",
        "answers": [
            "Спина",
            "Шея",
            "Уста",
            "Палец"
        ],
        "points": 3,
        "difficulty": {
            "__difficulty": 2
        },
        "correct_answer": 0
    },
    {
        "text": "В честь какого растения область Фриули-Венеция-Джулия в Италии ежегодно проводит трёхмесячный фестиваль?",
        "answers": [
            "Спаржа",
            "Лук",
            "Фасоль",
            "Артишок"
        ],
        "points": 3,
        "difficulty": {
            "__difficulty": 2
        },
        "correct_answer": 0
    },
    {
        "text": "Кто из перечисленных был пажом во времена Екатерины II?",
        "answers": [
            "А.Н. Радищев",
            "Н.М. Карамзин",
            "Д.И. Фонвизин",
            "Г.Р. Державин"
        ],
        "points": 3,
        "difficulty": {
            "__difficulty": 2
        },
        "correct_answer": 0
    },
    {
        "text": "Какой химический элемент назван в честь злого подземного гнома?",
        "answers": [
            "Кобальт",
            "Берилий",
            "Теллур",
            "Гафний"
        ],
        "points": 3,
        "difficulty": {
            "__difficulty": 2
        },
        "correct_answer": 0
    },
    {
        "text": "В какой из этих столиц бывших союзных республик раньше появилось метро?",
        "answers": [
            "Тбилиси",
            "Минск",
            "Ереван",
            "Баку"
        ],
        "points": 3,
        "difficulty": {
            "__difficulty": 2
        },
        "correct_answer": 0
    },
    {
        "text": "Что разбудило Спящую Красавицу?",
        "answers": [
            "Поцелуй принца",
            "Шумные соседи",
            "Будильник",
            "Телефон"
        ],
        "points": 1,
        "difficulty": {
            "__difficulty": 0
        },
        "correct_answer": 0
    },
    {
        "text": "Какого падежа в русском языке не существует?",
        "answers": [
            "Подложный",
            "Дательный",
            "Творительный",
            "Винительный"
        ],
        "points": 1,
        "difficulty": {
            "__difficulty": 0
        },
        "correct_answer": 0
    },
    {
        "text": "Как называется повесть Астрид Линдгрен: \"Малыш и...\"?",
        "answers": [
            "..Карлсон",
            "..Иван",
            "..собака",
            "..Взрослый"
        ],
        "points": 1,
        "difficulty": {
            "__difficulty": 0
        },
        "correct_answer": 0
    },
    {
        "text": "Что используют для поджаривания ломтиков хлеба?",
        "answers": [
            "Тостер",
            "Постер",
            "Винчестер",
            "Компостер"
        ],
        "points": 1,
        "difficulty": {
            "__difficulty": 0
        },
        "correct_answer": 0
    },
    {
        "text": "Какой обитатель водной стихии заслужил репутацию отшельника?",
        "answers": [
            "Рак",
            "Бычок",
            "Дельфин",
            "Медуза"
        ],
        "points": 1,
        "difficulty": {
            "__difficulty": 0
        },
        "correct_answer": 0
    },
    {
        "text": "Месторасположение какой из этих станций в Антарктиде совпадает с полюсом холода?",
        "answers": [
            "\"Восток\"",
            "\"Пионерская\"",
            "\"Молодёжная\"",
            "\"Мирный\""
        ],
        "points": 2,
        "difficulty": {
            "__difficulty": 1
        },
        "correct_answer": 0
    },
    {
        "text": "Какой персонаж оперы Глинки \"Руслан и Людмила\" не поёт?",
        "answers": [
            "Черномор",
            "Ратмир",
            "Наина",
            "Финн"
        ],
        "points": 2,
        "difficulty": {
            "__difficulty": 1
        },
        "correct_answer": 0
    },
    {
        "text": "Сколько корон на Государственном гербе РФ?",
        "answers": [
            "Три",
            "Одна",
            "Две",
            "Пять"
        ],
        "points": 2,
        "difficulty": {
            "__difficulty": 1
        },
        "correct_answer": 0
    },
    {
        "text": "На территории какой страны был открыт золотоносный район Клондайк?",
        "answers": [
            "Канада",
            "США",
            "Мексика",
            "Венесуэла"
        ],
        "points": 2,
        "difficulty": {
            "__difficulty": 1
        },
        "correct_answer": 0
    },
    {
        "text": "Где проходила Олимпиада, на которой бросок А. Белова вывел баскетбольную команду СССР в чемпионы?",
        "answers": [
            "Мюнхен",
            "Рим",
            "Монреаль",
            "Мехико"
        ],
        "points": 2,
        "difficulty": {
            "__difficulty": 1
        },
        "correct_answer": 0
    },
    {
        "text": "Реки с каким названием нет на территории России?",
        "answers": [
            "Спина",
            "Шея",
            "Уста",
            "Палец"
        ],
        "points": 3,
        "difficulty": {
            "__difficulty": 2
        },
        "correct_answer": 0
    },
    {
        "text": "Какой химический элемент назван в честь злого подземного гнома?",
        "answers": [
            "Кобальт",
            "Берилий",
            "Теллур",
            "Гафний"
        ],
        "points": 3,
        "difficulty": {
            "__difficulty": 2
        },
        "correct_answer": 0
    },
    {
        "text": "В честь какого растения область Фриули-Венеция-Джулия в Италии ежегодно проводит трёхмесячный фестиваль?",
        "answers": [
            "Спаржа",
            "Лук",
            "Фасоль",
            "Артишок"
        ],
        "points": 3,
        "difficulty": {
            "__difficulty": 2
        },
        "correct_answer": 0
    },
    {
        "text": "Кто из перечисленных был пажом во времена Екатерины II?",
        "answers": [
            "А.Н. Радищев",
            "Н.М. Карамзин",
            "Д.И. Фонвизин",
            "Г.Р. Державин"
        ],
        "points": 3,
        "difficulty": {
            "__difficulty": 2
        },
        "correct_answer": 0
    },
    {
        "text": "В какой из этих столиц бывших союзных республик раньше появилось метро?",
        "answers": [
            "Тбилиси",
            "Минск",
            "Ереван",
            "Баку"
        ],
        "points": 3,
        "difficulty": {
            "__difficulty": 2
        },
        "correct_answer": 0
    },
    {
        "text": "Какого падежа в русском языке не существует?",
        "answers": [
            "Подложный",
            "Дательный",
            "Творительный",
            "Винительный"
        ],
        "points": 1,
        "difficulty": {
            "__difficulty": 0
        },
        "correct_answer": 0
    },
    {
        "text": "Что используют для поджаривания ломтиков хлеба?",
        "answers": [
            "Тостер",
            "Постер",
            "Винчестер",
            "Компостер"
        ],
        "points": 1,
        "difficulty": {
            "__difficulty": 0
        },
        "correct_answer": 0
    },
    {
        "text": "Что разбудило Спящую Красавицу?",
        "answers": [
            "Поцелуй принца",
            "Шумные соседи",
            "Будильник",
            "Телефон"
        ],
        "points": 1,
        "difficulty": {
            "__difficulty": 0
        },
        "correct_answer": 0
    },
    {
        "text": "Как называется повесть Астрид Линдгрен: \"Малыш и...\"?",
        "answers": [
            "..Карлсон",
            "..Иван",
            "..собака",
            "..Взрослый"
        ],
        "points": 1,
        "difficulty": {
            "__difficulty": 0
        },
        "correct_answer": 0
    },
    {
        "text": "Какой обитатель водной стихии заслужил репутацию отшельника?",
        "answers": [
            "Рак",
            "Бычок",
            "Дельфин",
            "Медуза"
        ],
        "points": 1,
        "difficulty": {
            "__difficulty": 0
        },
        "correct_answer": 0
    },
    {
        "text": "Какой персонаж оперы Глинки \"Руслан и Людмила\" не поёт?",
        "answers": [
            "Черномор",
            "Ратмир",
            "Наина",
            "Финн"
        ],
        "points": 2,
        "difficulty": {
            "__difficulty": 1
        },
        "correct_answer": 0
    },
    {
        "text": "На территории какой страны был открыт золотоносный район Клондайк?",
        "answers": [
            "Канада",
            "США",
            "Мексика",
            "Венесуэла"
        ],
        "points": 2,
        "difficulty": {
            "__difficulty": 1
        },
        "correct_answer": 0
    },
    {
        "text": "Сколько корон на Государственном гербе РФ?",
        "answers": [
            "Три",
            "Одна",
            "Две",
            "Пять"
        ],
        "points": 2,
        "difficulty": {
            "__difficulty": 1
        },
        "correct_answer": 0
    },
    {
        "text": "Где проходила Олимпиада, на которой бросок А. Белова вывел баскетбольную команду СССР в чемпионы?",
        "answers": [
            "Мюнхен",
            "Рим",
            "Монреаль",
            "Мехико"
        ],
        "points": 2,
        "difficulty": {
            "__difficulty": 1
        },
        "correct_answer": 0
    },
    {
        "text": "Месторасположение какой из этих станций в Антарктиде совпадает с полюсом холода?",
        "answers": [
            "\"Восток\"",
            "\"Пионерская\"",
            "\"Молодёжная\"",
            "\"Мирный\""
        ],
        "points": 2,
        "difficulty": {
            "__difficulty": 1
        },
        "correct_answer": 0
    },
    {
        "text": "Кто из перечисленных был пажом во времена Екатерины II?",
        "answers": [
            "А.Н. Радищев",
            "Н.М. Карамзин",
            "Д.И. Фонвизин",
            "Г.Р. Державин"
        ],
        "points": 3,
        "difficulty": {
            "__difficulty": 2
        },
        "correct_answer": 0
    },
    {
        "text": "Реки с каким названием нет на территории России?",
        "answers": [
            "Спина",
            "Шея",
            "Уста",
            "Палец"
        ],
        "points": 3,
        "difficulty": {
            "__difficulty": 2
        },
        "correct_answer": 0
    },
    {
        "text": "В честь какого растения область Фриули-Венеция-Джулия в Италии ежегодно проводит трёхмесячный фестиваль?",
        "answers": [
            "Спаржа",
            "Лук",
            "Фасоль",
            "Артишок"
        ],
        "points": 3,
        "difficulty": {
            "__difficulty": 2
        },
        "correct_answer": 0
    },
    {
        "text": "Какой химический элемент назван в честь злого подземного гнома?",
        "answers": [
            "Кобальт",
            "Берилий",
            "Теллур",
            "Гафний"
        ],
        "points": 3,
        "difficulty": {
            "__difficulty": 2
        },
        "correct_answer": 0
    },
    {
        "text": "В какой из этих столиц бывших союзных республик раньше появилось метро?",
        "answers": [
            "Тбилиси",
            "Минск",
            "Ереван",
            "Баку"
        ],
        "points": 3,
        "difficulty": {
            "__difficulty": 2
        },
        "correct_answer": 0
    },
    {
        "text": "Что разбудило Спящую Красавицу?",
        "answers": [
            "Поцелуй принца",
            "Шумные соседи",
            "Будильник",
            "Телефон"
        ],
        "points": 1,
        "difficulty": {
            "__difficulty": 0
        },
        "correct_answer": 0
    },
    {
        "text": "Как называется повесть Астрид Линдгрен: \"Малыш и...\"?",
        "answers": [
            "..Карлсон",
            "..Иван",
            "..собака",
            "..Взрослый"
        ],
        "points": 1,
        "difficulty": {
            "__difficulty": 0
        },
        "correct_answer": 0
    },
    {
        "text": "Что используют для поджаривания ломтиков хлеба?",
        "answers": [
            "Тостер",
            "Постер",
            "Винчестер",
            "Компостер"
        ],
        "points": 1,
        "difficulty": {
            "__difficulty": 0
        },
        "correct_answer": 0
    },
    {
        "text": "Какого падежа в русском языке не существует?",
        "answers": [
            "Подложный",
            "Дательный",
            "Творительный",
            "Винительный"
        ],
        "points": 1,
        "difficulty": {
            "__difficulty": 0
        },
        "correct_answer": 0
    },
    {
        "text": "Какой обитатель водной стихии заслужил репутацию отшельника?",
        "answers": [
            "Рак",
            "Бычок",
            "Дельфин",
            "Медуза"
        ],
        "points": 1,
        "difficulty": {
            "__difficulty": 0
        },
        "correct_answer": 0
    },
    {
        "text": "Где проходила Олимпиада, на которой бросок А. Белова вывел баскетбольную команду СССР в чемпионы?",
        "answers": [
            "Мюнхен",
            "Рим",
            "Монреаль",
            "Мехико"
        ],
        "points": 2,
        "difficulty": {
            "__difficulty": 1
        },
        "correct_answer": 0
    },
    {
        "text": "Месторасположение какой из этих станций в Антарктиде совпадает с полюсом холода?",
        "answers": [
            "\"Восток\"",
            "\"Пионерская\"",
            "\"Молодёжная\"",
            "\"Мирный\""
        ],
        "points": 2,
        "difficulty": {
            "__difficulty": 1
        },
        "correct_answer": 0
    },
    {
        "text": "Сколько корон на Государственном гербе РФ?",
        "answers": [
            "Три",
            "Одна",
            "Две",
            "Пять"
        ],
        "points": 2,
        "difficulty": {
            "__difficulty": 1
        },
        "correct_answer": 0
    },
    {
        "text": "Какой персонаж оперы Глинки \"Руслан и Людмила\" не поёт?",
        "answers": [
            "Черномор",
            "Ратмир",
            "Наина",
            "Финн"
        ],
        "points": 2,
        "difficulty": {
            "__difficulty": 1
        },
        "correct_answer": 0
    },
    {
        "text": "На территории какой страны был открыт золотоносный район Клондайк?",
        "answers": [
            "Канада",
            "США",
            "Мексика",
            "Венесуэла"
        ],
        "points": 2,
        "difficulty": {
            "__difficulty": 1
        },
        "correct_answer": 0
    },
    {
        "text": "Какой химический элемент назван в честь злого подземного гнома?",
        "answers": [
            "Кобальт",
            "Берилий",
            "Теллур",
            "Гафний"
        ],
        "points": 3,
        "difficulty": {
            "__difficulty": 2
        },
        "correct_answer": 0
    },
    {
        "text": "В какой из этих столиц бывших союзных республик раньше появилось метро?",
        "answers": [
            "Тбилиси",
            "Минск",
            "Ереван",
            "Баку"
        ],
        "points": 3,
        "difficulty": {
            "__difficulty": 2
        },
        "correct_answer": 0
    },
    {
        "text": "В честь какого растения область Фриули-Венеция-Джулия в Италии ежегодно проводит трёхмесячный фестиваль?",
        "answers": [
            "Спаржа",
            "Лук",
            "Фасоль",
            "Артишок"
        ],
        "points": 3,
        "difficulty": {
            "__difficulty": 2
        },
        "correct_answer": 0
    },
    {
        "text": "Кто из перечисленных был пажом во времена Екатерины II?",
        "answers": [
            "А.Н. Радищев",
            "Н.М. Карамзин",
            "Д.И. Фонвизин",
            "Г.Р. Державин"
        ],
        "points": 3,
        "difficulty": {
            "__difficulty": 2
        },
        "correct_answer": 0
    },
    {
        "text": "Реки с каким названием нет на территории России?",
        "answers": [
            "Спина",
            "Шея",
            "Уста",
            "Палец"
        ],
        "points": 3,
        "difficulty": {
            "__difficulty": 2
        },
        "correct_answer": 0
    },
    {
        "text": "Как называется повесть Астрид Линдгрен: \"Малыш и...\"?",
        "answers": [
            "..Карлсон",
            "..Иван",
            "..собака",
            "..Взрослый"
        ],
        "points": 1,
        "difficulty": {
            "__difficulty": 0
        },
        "correct_answer": 0
    },
    {
        "text": "Что используют для поджаривания ломтиков хлеба?",
        "answers": [
            "Тостер",
            "Постер",
            "Винчестер",
            "Компостер"
        ],
        "points": 1,
        "difficulty": {
            "__difficulty": 0
        },
        "correct_answer": 0
    },
    {
        "text": "Какой обитатель водной стихии заслужил репутацию отшельника?",
        "answers": [
            "Рак",
            "Бычок",
            "Дельфин",
            "Медуза"
        ],
        "points": 1,
        "difficulty": {
            "__difficulty": 0
        },
        "correct_answer": 0
    },
    {
        "text": "Что разбудило Спящую Красавицу?",
        "answers": [
            "Поцелуй принца",
            "Шумные соседи",
            "Будильник",
            "Телефон"
        ],
        "points": 1,
        "difficulty": {
            "__difficulty": 0
        },
        "correct_answer": 0
    },
    {
        "text": "Какого падежа в русском языке не существует?",
        "answers": [
            "Подложный",
            "Дательный",
            "Творительный",
            "Винительный"
        ],
        "points": 1,
        "difficulty": {
            "__difficulty": 0
        },
        "correct_answer": 0
    },
    {
        "text": "Месторасположение какой из этих станций в Антарктиде совпадает с полюсом холода?",
        "answers": [
            "\"Восток\"",
            "\"Пионерская\"",
            "\"Молодёжная\"",
            "\"Мирный\""
        ],
        "points": 2,
        "difficulty": {
            "__difficulty": 1
        },
        "correct_answer": 0
    },
    {
        "text": "На территории какой страны был открыт золотоносный район Клондайк?",
        "answers": [
            "Канада",
            "США",
            "Мексика",
            "Венесуэла"
        ],
        "points": 2,
        "difficulty": {
            "__difficulty": 1
        },
        "correct_answer": 0
    },
    {
        "text": "Сколько корон на Государственном гербе РФ?",
        "answers": [
            "Три",
            "Одна",
            "Две",
            "Пять"
        ],
        "points": 2,
        "difficulty": {
            "__difficulty": 1
        },
        "correct_answer": 0
    },
    {
        "text": "Какой персонаж оперы Глинки \"Руслан и Людмила\" не поёт?",
        "answers": [
            "Черномор",
            "Ратмир",
            "Наина",
            "Финн"
        ],
        "points": 2,
        "difficulty": {
            "__difficulty": 1
        },
        "correct_answer": 0
    },
    {
        "text": "Где проходила Олимпиада, на которой бросок А. Белова вывел баскетбольную команду СССР в чемпионы?",
        "answers": [
            "Мюнхен",
            "Рим",
            "Монреаль",
            "Мехико"
        ],
        "points": 2,
        "difficulty": {
            "__difficulty": 1
        },
        "correct_answer": 0
    },
    {
        "text": "В честь какого растения область Фриули-Венеция-Джулия в Италии ежегодно проводит трёхмесячный фестиваль?",
        "answers": [
            "Спаржа",
            "Лук",
            "Фасоль",
            "Артишок"
        ],
        "points": 3,
        "difficulty": {
            "__difficulty": 2
        },
        "correct_answer": 0
    },
    {
        "text": "В какой из этих столиц бывших союзных республик раньше появилось метро?",
        "answers": [
            "Тбилиси",
            "Минск",
            "Ереван",
            "Баку"
        ],
        "points": 3,
        "difficulty": {
            "__difficulty": 2
        },
        "correct_answer": 0
    },
    {
        "text": "Какой химический элемент назван в честь злого подземного гнома?",
        "answers": [
            "Кобальт",
            "Берилий",
            "Теллур",
            "Гафний"
        ],
        "points": 3,
        "difficulty": {
            "__difficulty": 2
        },
        "correct_answer": 0
    },
    {
        "text": "Кто из перечисленных был пажом во времена Екатерины II?",
        "answers": [
            "А.Н. Радищев",
            "Н.М. Карамзин",
            "Д.И. Фонвизин",
            "Г.Р. Державин"
        ],
        "points": 3,
        "difficulty": {
            "__difficulty": 2
        },
        "correct_answer": 0
    },
    {
        "text": "Реки с каким названием нет на территории России?",
        "answers": [
            "Спина",
            "Шея",
            "Уста",
            "Палец"
        ],
        "points": 3,
        "difficulty": {
            "__difficulty": 2
        },
        "correct_answer": 0
    },
    {
        "text": "Что разбудило Спящую Красавицу?",
        "answers": [
            "Поцелуй принца",
            "Шумные соседи",
            "Будильник",
            "Телефон"
        ],
        "points": 1,
        "difficulty": {
            "__difficulty": 0
        },
        "correct_answer": 0
    },
    {
        "text": "Какого падежа в русском языке не существует?",
        "answers": [
            "Подложный",
            "Дательный",
            "Творительный",
            "Винительный"
        ],
        "points": 1,
        "difficulty": {
            "__difficulty": 0
        },
        "correct_answer": 0
    },
    {
        "text": "Как называется повесть Астрид Линдгрен: \"Малыш и...\"?",
        "answers": [
            "..Карлсон",
            "..Иван",
            "..собака",
            "..Взрослый"
        ],
        "points": 1,
        "difficulty": {
            "__difficulty": 0
        },
        "correct_answer": 0
    },
    {
        "text": "Что используют для поджаривания ломтиков хлеба?",
        "answers": [
            "Тостер",
            "Постер",
            "Винчестер",
            "Компостер"
        ],
        "points": 1,
        "difficulty": {
            "__difficulty": 0
        },
        "correct_answer": 0
    },
    {
        "text": "Какой обитатель водной стихии заслужил репутацию отшельника?",
        "answers": [
            "Рак",
            "Бычок",
            "Дельфин",
            "Медуза"
        ],
        "points": 1,
        "difficulty": {
            "__difficulty": 0
        },
        "correct_answer": 0
    },
    {
        "text": "Где проходила Олимпиада, на которой бросок А. Белова вывел баскетбольную команду СССР в чемпионы?",
        "answers": [
            "Мюнхен",
            "Рим",
            "Монреаль",
            "Мехико"
        ],
        "points": 2,
        "difficulty": {
            "__difficulty": 1
        },
        "correct_answer": 0
    },
    {
        "text": "На территории какой страны был открыт золотоносный район Клондайк?",
        "answers": [
            "Канада",
            "США",
            "Мексика",
            "Венесуэла"
        ],
        "points": 2,
        "difficulty": {
            "__difficulty": 1
        },
        "correct_answer": 0
    },
    {
        "text": "Какой персонаж оперы Глинки \"Руслан и Людмила\" не поёт?",
        "answers": [
            "Черномор",
            "Ратмир",
            "Наина",
            "Финн"
        ],
        "points": 2,
        "difficulty": {
            "__difficulty": 1
        },
        "correct_answer": 0
    },
    {
        "text": "Сколько корон на Государственном гербе РФ?",
        "answers": [
            "Три",
            "Одна",
            "Две",
            "Пять"
        ],
        "points": 2,
        "difficulty": {
            "__difficulty": 1
        },
        "correct_answer": 0
    },
    {
        "text": "Месторасположение какой из этих станций в Антарктиде совпадает с полюсом холода?",
        "answers": [
            "\"Восток\"",
            "\"Пионерская\"",
            "\"Молодёжная\"",
            "\"Мирный\""
        ],
        "points": 2,
        "difficulty": {
            "__difficulty": 1
        },
        "correct_answer": 0
    },
    {
        "text": "Кто из перечисленных был пажом во времена Екатерины II?",
        "answers": [
            "А.Н. Радищев",
            "Н.М. Карамзин",
            "Д.И. Фонвизин",
            "Г.Р. Державин"
        ],
        "points": 3,
        "difficulty": {
            "__difficulty": 2
        },
        "correct_answer": 0
    },
    {
        "text": "Какой химический элемент назван в честь злого подземного гнома?",
        "answers": [
            "Кобальт",
            "Берилий",
            "Теллур",
            "Гафний"
        ],
        "points": 3,
        "difficulty": {
            "__difficulty": 2
        },
        "correct_answer": 0
    },
    {
        "text": "В честь какого растения область Фриули-Венеция-Джулия в Италии ежегодно проводит трёхмесячный фестиваль?",
        "answers": [
            "Спаржа",
            "Лук",
            "Фасоль",
            "Артишок"
        ],
        "points": 3,
        "difficulty": {
            "__difficulty": 2
        },
        "correct_answer": 0
    },
    {
        "text": "В какой из этих столиц бывших союзных республик раньше появилось метро?",
        "answers": [
            "Тбилиси",
            "Минск",
            "Ереван",
            "Баку"
        ],
        "points": 3,
        "difficulty": {
            "__difficulty": 2
        },
        "correct_answer": 0
    },
    {
        "text": "Реки с каким названием нет на территории России?",
        "answers": [
            "Спина",
            "Шея",
            "Уста",
            "Палец"
        ],
        "points": 3,
        "difficulty": {
            "__difficulty": 2
        },
        "correct_answer": 0
    },
    {
        "text": "Как называется повесть Астрид Линдгрен: \"Малыш и...\"?",
        "answers": [
            "..Карлсон",
            "..Иван",
            "..собака",
            "..Взрослый"
        ],
        "points": 1,
        "difficulty": {
            "__difficulty": 0
        },
        "correct_answer": 0
    },
    {
        "text": "Что разбудило Спящую Красавицу?",
        "answers": [
            "Поцелуй принца",
            "Шумные соседи",
            "Будильник",
            "Телефон"
        ],
        "points": 1,
        "difficulty": {
            "__difficulty": 0
        },
        "correct_answer": 0
    },
    {
        "text": "Какой обитатель водной стихии заслужил репутацию отшельника?",
        "answers": [
            "Рак",
            "Бычок",
            "Дельфин",
            "Медуза"
        ],
        "points": 1,
        "difficulty": {
            "__difficulty": 0
        },
        "correct_answer": 0
    },
    {
        "text": "Что используют для поджаривания ломтиков хлеба?",
        "answers": [
            "Тостер",
            "Постер",
            "Винчестер",
            "Компостер"
        ],
        "points": 1,
        "difficulty": {
            "__difficulty": 0
        },
        "correct_answer": 0
    },
    {
        "text": "Какого падежа в русском языке не существует?",
        "answers": [
            "Подложный",
            "Дательный",
            "Творительный",
            "Винительный"
        ],
        "points": 1,
        "difficulty": {
            "__difficulty": 0
        },
        "correct_answer": 0
    },
    {
        "text": "Где проходила Олимпиада, на которой бросок А. Белова вывел баскетбольную команду СССР в чемпионы?",
        "answers": [
            "Мюнхен",
            "Рим",
            "Монреаль",
            "Мехико"
        ],
        "points": 2,
        "difficulty": {
            "__difficulty": 1
        },
        "correct_answer": 0
    },
    {
        "text": "Месторасположение какой из этих станций в Антарктиде совпадает с полюсом холода?",
        "answers": [
            "\"Восток\"",
            "\"Пионерская\"",
            "\"Молодёжная\"",
            "\"Мирный\""
        ],
        "points": 2,
        "difficulty": {
            "__difficulty": 1
        },
        "correct_answer": 0
    },
    {
        "text": "На территории какой страны был открыт золотоносный район Клондайк?",
        "answers": [
            "Канада",
            "США",
            "Мексика",
            "Венесуэла"
        ],
        "points": 2,
        "difficulty": {
            "__difficulty": 1
        },
        "correct_answer": 0
    },
    {
        "text": "Сколько корон на Государственном гербе РФ?",
        "answers": [
            "Три",
            "Одна",
            "Две",
            "Пять"
        ],
        "points": 2,
        "difficulty": {
            "__difficulty": 1
        },
        "correct_answer": 0
    },
    {
        "text": "Какой персонаж оперы Глинки \"Руслан и Людмила\" не поёт?",
        "answers": [
            "Черномор",
            "Ратмир",
            "Наина",
            "Финн"
        ],
        "points": 2,
        "difficulty": {
            "__difficulty": 1
        },
        "correct_answer": 0
    },
    {
        "text": "Кто из перечисленных был пажом во времена Екатерины II?",
        "answers": [
            "А.Н. Радищев",
            "Н.М. Карамзин",
            "Д.И. Фонвизин",
            "Г.Р. Державин"
        ],
        "points": 3,
        "difficulty": {
            "__difficulty": 2
        },
        "correct_answer": 0
    },
    {
        "text": "В какой из этих столиц бывших союзных республик раньше появилось метро?",
        "answers": [
            "Тбилиси",
            "Минск",
            "Ереван",
            "Баку"
        ],
        "points": 3,
        "difficulty": {
            "__difficulty": 2
        },
        "correct_answer": 0
    },
    {
        "text": "Какой химический элемент назван в честь злого подземного гнома?",
        "answers": [
            "Кобальт",
            "Берилий",
            "Теллур",
            "Гафний"
        ],
        "points": 3,
        "difficulty": {
            "__difficulty": 2
        },
        "correct_answer": 0
    },
    {
        "text": "Реки с каким названием нет на территории России?",
        "answers": [
            "Спина",
            "Шея",
            "Уста",
            "Палец"
        ],
        "points": 3,
        "difficulty": {
            "__difficulty": 2
        },
        "correct_answer": 0
    },
    {
        "text": "В честь какого растения область Фриули-Венеция-Джулия в Италии ежегодно проводит трёхмесячный фестиваль?",
        "answers": [
            "Спаржа",
            "Лук",
            "Фасоль",
            "Артишок"
        ],
        "points": 3,
        "difficulty": {
            "__difficulty": 2
        },
        "correct_answer": 0
    },
    {
        "text": "Какого падежа в русском языке не существует?",
        "answers": [
            "Подложный",
            "Дательный",
            "Творительный",
            "Винительный"
        ],
        "points": 1,
        "difficulty": {
            "__difficulty": 0
        },
        "correct_answer": 0
    },
    {
        "text": "Как называется повесть Астрид Линдгрен: \"Малыш и...\"?",
        "answers": [
            "..Карлсон",
            "..Иван",
            "..собака",
            "..Взрослый"
        ],
        "points": 1,
        "difficulty": {
            "__difficulty": 0
        },
        "correct_answer": 0
    },
    {
        "text": "Какой обитатель водной стихии заслужил репутацию отшельника?",
        "answers": [
            "Рак",
            "Бычок",
            "Дельфин",
            "Медуза"
        ],
        "points": 1,
        "difficulty": {
            "__difficulty": 0
        },
        "correct_answer": 0
    },
    {
        "text": "Что используют для поджаривания ломтиков хлеба?",
        "answers": [
            "Тостер",
            "Постер",
            "Винчестер",
            "Компостер"
        ],
        "points": 1,
        "difficulty": {
            "__difficulty": 0
        },
        "correct_answer": 0
    },
    {
        "text": "Что разбудило Спящую Красавицу?",
        "answers": [
            "Поцелуй принца",
            "Шумные соседи",
            "Будильник",
            "Телефон"
        ],
        "points": 1,
        "difficulty": {
            "__difficulty": 0
        },
        "correct_answer": 0
    },
    {
        "text": "Месторасположение какой из этих станций в Антарктиде совпадает с полюсом холода?",
        "answers": [
            "\"Восток\"",
            "\"Пионерская\"",
            "\"Молодёжная\"",
            "\"Мирный\""
        ],
        "points": 2,
        "difficulty": {
            "__difficulty": 1
        },
        "correct_answer": 0
    },
    {
        "text": "Где проходила Олимпиада, на которой бросок А. Белова вывел баскетбольную команду СССР в чемпионы?",
        "answers": [
            "Мюнхен",
            "Рим",
            "Монреаль",
            "Мехико"
        ],
        "points": 2,
        "difficulty": {
            "__difficulty": 1
        },
        "correct_answer": 0
    },
    {
        "text": "На территории какой страны был открыт золотоносный район Клондайк?",
        "answers": [
            "Канада",
            "США",
            "Мексика",
            "Венесуэла"
        ],
        "points": 2,
        "difficulty": {
            "__difficulty": 1
        },
        "correct_answer": 0
    },
    {
        "text": "Сколько корон на Государственном гербе РФ?",
        "answers": [
            "Три",
            "Одна",
            "Две",
            "Пять"
        ],
        "points": 2,
        "difficulty": {
            "__difficulty": 1
        },
        "correct_answer": 0
    },
    {
        "text": "Какой персонаж оперы Глинки \"Руслан и Людмила\" не поёт?",
        "answers": [
            "Черномор",
            "Ратмир",
            "Наина",
            "Финн"
        ],
        "points": 2,
        "difficulty": {
            "__difficulty": 1
        },
        "correct_answer": 0
    },
    {
        "text": "В честь какого растения область Фриули-Венеция-Джулия в Италии ежегодно проводит трёхмесячный фестиваль?",
        "answers": [
            "Спаржа",
            "Лук",
            "Фасоль",
            "Артишок"
        ],
        "points": 3,
        "difficulty": {
            "__difficulty": 2
        },
        "correct_answer": 0
    },
    {
        "text": "Реки с каким названием нет на территории России?",
        "answers": [
            "Спина",
            "Шея",
            "Уста",
            "Палец"
        ],
        "points": 3,
        "difficulty": {
            "__difficulty": 2
        },
        "correct_answer": 0
    },
    {
        "text": "В какой из этих столиц бывших союзных республик раньше появилось метро?",
        "answers": [
            "Тбилиси",
            "Минск",
            "Ереван",
            "Баку"
        ],
        "points": 3,
        "difficulty": {
            "__difficulty": 2
        },
        "correct_answer": 0
    },
    {
        "text": "Кто из перечисленных был пажом во времена Екатерины II?",
        "answers": [
            "А.Н. Радищев",
            "Н.М. Карамзин",
            "Д.И. Фонвизин",
            "Г.Р. Державин"
        ],
        "points": 3,
        "difficulty": {
            "__difficulty": 2
        },
        "correct_answer": 0
    },
    {
        "text": "Какой химический элемент назван в честь злого подземного гнома?",
        "answers": [
            "Кобальт",
            "Берилий",
            "Теллур",
            "Гафний"
        ],
        "points": 3,
        "difficulty": {
            "__difficulty": 2
        },
        "correct_answer": 0
    },
    {
        "text": "Что разбудило Спящую Красавицу?",
        "answers": [
            "Поцелуй принца",
            "Шумные соседи",
            "Будильник",
            "Телефон"
        ],
        "points": 1,
        "difficulty": {
            "__difficulty": 0
        },
        "correct_answer": 0
    },
    {
        "text": "Как называется повесть Астрид Линдгрен: \"Малыш и...\"?",
        "answers": [
            "..Карлсон",
            "..Иван",
            "..собака",
            "..Взрослый"
        ],
        "points": 1,
        "difficulty": {
            "__difficulty": 0
        },
        "correct_answer": 0
    },
    {
        "text": "Какой обитатель водной стихии заслужил репутацию отшельника?",
        "answers": [
            "Рак",
            "Бычок",
            "Дельфин",
            "Медуза"
        ],
        "points": 1,
        "difficulty": {
            "__difficulty": 0
        },
        "correct_answer": 0
    },
    {
        "text": "Что используют для поджаривания ломтиков хлеба?",
        "answers": [
            "Тостер",
            "Постер",
            "Винчестер",
            "Компостер"
        ],
        "points": 1,
        "difficulty": {
            "__difficulty": 0
        },
        "correct_answer": 0
    },
    {
        "text": "Какого падежа в русском языке не существует?",
        "answers": [
            "Подложный",
            "Дательный",
            "Творительный",
            "Винительный"
        ],
        "points": 1,
        "difficulty": {
            "__difficulty": 0
        },
        "correct_answer": 0
    },
    {
        "text": "Где проходила Олимпиада, на которой бросок А. Белова вывел баскетбольную команду СССР в чемпионы?",
        "answers": [
            "Мюнхен",
            "Рим",
            "Монреаль",
            "Мехико"
        ],
        "points": 2,
        "difficulty": {
            "__difficulty": 1
        },
        "correct_answer": 0
    },
    {
        "text": "Сколько корон на Государственном гербе РФ?",
        "answers": [
            "Три",
            "Одна",
            "Две",
            "Пять"
        ],
        "points": 2,
        "difficulty": {
            "__difficulty": 1
        },
        "correct_answer": 0
    },
    {
        "text": "Какой персонаж оперы Глинки \"Руслан и Людмила\" не поёт?",
        "answers": [
            "Черномор",
            "Ратмир",
            "Наина",
            "Финн"
        ],
        "points": 2,
        "difficulty": {
            "__difficulty": 1
        },
        "correct_answer": 0
    },
    {
        "text": "На территории какой страны был открыт золотоносный район Клондайк?",
        "answers": [
            "Канада",
            "США",
            "Мексика",
            "Венесуэла"
        ],
        "points": 2,
        "difficulty": {
            "__difficulty": 1
        },
        "correct_answer": 0
    },
    {
        "text": "Месторасположение какой из этих станций в Антарктиде совпадает с полюсом холода?",
        "answers": [
            "\"Восток\"",
            "\"Пионерская\"",
            "\"Молодёжная\"",
            "\"Мирный\""
        ],
        "points": 2,
        "difficulty": {
            "__difficulty": 1
        },
        "correct_answer": 0
    },
    {
        "text": "Кто из перечисленных был пажом во времена Екатерины II?",
        "answers": [
            "А.Н. Радищев",
            "Н.М. Карамзин",
            "Д.И. Фонвизин",
            "Г.Р. Державин"
        ],
        "points": 3,
        "difficulty": {
            "__difficulty": 2
        },
        "correct_answer": 0
    },
    {
        "text": "Какой химический элемент назван в честь злого подземного гнома?",
        "answers": [
            "Кобальт",
            "Берилий",
            "Теллур",
            "Гафний"
        ],
        "points": 3,
        "difficulty": {
            "__difficulty": 2
        },
        "correct_answer": 0
    },
    {
        "text": "В какой из этих столиц бывших союзных республик раньше появилось метро?",
        "answers": [
            "Тбилиси",
            "Минск",
            "Ереван",
            "Баку"
        ],
        "points": 3,
        "difficulty": {
            "__difficulty": 2
        },
        "correct_answer": 0
    },
    {
        "text": "В честь какого растения область Фриули-Венеция-Джулия в Италии ежегодно проводит трёхмесячный фестиваль?",
        "answers": [
            "Спаржа",
            "Лук",
            "Фасоль",
            "Артишок"
        ],
        "points": 3,
        "difficulty": {
            "__difficulty": 2
        },
        "correct_answer": 0
    },
    {
        "text": "Реки с каким названием нет на территории России?",
        "answers": [
            "Спина",
            "Шея",
            "Уста",
            "Палец"
        ],
        "points": 3,
        "difficulty": {
            "__difficulty": 2
        },
        "correct_answer": 0
    },
    {
        "text": "Что используют для поджаривания ломтиков хлеба?",
        "answers": [
            "Тостер",
            "Постер",
            "Винчестер",
            "Компостер"
        ],
        "points": 1,
        "difficulty": {
            "__difficulty": 0
        },
        "correct_answer": 0
    },
    {
        "text": "Какого падежа в русском языке не существует?",
        "answers": [
            "Подложный",
            "Дательный",
            "Творительный",
            "Винительный"
        ],
        "points": 1,
        "difficulty": {
            "__difficulty": 0
        },
        "correct_answer": 0
    },
    {
        "text": "Какой обитатель водной стихии заслужил репутацию отшельника?",
        "answers": [
            "Рак",
            "Бычок",
            "Дельфин",
            "Медуза"
        ],
        "points": 1,
        "difficulty": {
            "__difficulty": 0
        },
        "correct_answer": 0
    },
    {
        "text": "Как называется повесть Астрид Линдгрен: \"Малыш и...\"?",
        "answers": [
            "..Карлсон",
            "..Иван",
            "..собака",
            "..Взрослый"
        ],
        "points": 1,
        "difficulty": {
            "__difficulty": 0
        },
        "correct_answer": 0
    },
    {
        "text": "Что разбудило Спящую Красавицу?",
        "answers": [
            "Поцелуй принца",
            "Шумные соседи",
            "Будильник",
            "Телефон"
        ],
        "points": 1,
        "difficulty": {
            "__difficulty": 0
        },
        "correct_answer": 0
    },
    {
        "text": "На территории какой страны был открыт золотоносный район Клондайк?",
        "answers": [
            "Канада",
            "США",
            "Мексика",
            "Венесуэла"
        ],
        "points": 2,
        "difficulty": {
            "__difficulty": 1
        },
        "correct_answer": 0
    },
    {
        "text": "Какой персонаж оперы Глинки \"Руслан и Людмила\" не поёт?",
        "answers": [
            "Черномор",
            "Ратмир",
            "Наина",
            "Финн"
        ],
        "points": 2,
        "difficulty": {
            "__difficulty": 1
        },
        "correct_answer": 0
    },
    {
        "text": "Где проходила Олимпиада, на которой бросок А. Белова вывел баскетбольную команду СССР в чемпионы?",
        "answers": [
            "Мюнхен",
            "Рим",
            "Монреаль",
            "Мехико"
        ],
        "points": 2,
        "difficulty": {
            "__difficulty": 1
        },
        "correct_answer": 0
    },
    {
        "text": "Сколько корон на Государственном гербе РФ?",
        "answers": [
            "Три",
            "Одна",
            "Две",
            "Пять"
        ],
        "points": 2,
        "difficulty": {
            "__difficulty": 1
        },
        "correct_answer": 0
    },
    {
        "text": "Месторасположение какой из этих станций в Антарктиде совпадает с полюсом холода?",
        "answers": [
            "\"Восток\"",
            "\"Пионерская\"",
            "\"Молодёжная\"",
            "\"Мирный\""
        ],
        "points": 2,
        "difficulty": {
            "__difficulty": 1
        },
        "correct_answer": 0
    },
    {
        "text": "Какой химический элемент назван в честь злого подземного гнома?",
        "answers": [
            "Кобальт",
            "Берилий",
            "Теллур",
            "Гафний"
        ],
        "points": 3,
        "difficulty": {
            "__difficulty": 2
        },
        "correct_answer": 0
    },
    {
        "text": "Кто из перечисленных был пажом во времена Екатерины II?",
        "answers": [
            "А.Н. Радищев",
            "Н.М. Карамзин",
            "Д.И. Фонвизин",
            "Г.Р. Державин"
        ],
        "points": 3,
        "difficulty": {
            "__difficulty": 2
        },
        "correct_answer": 0
    },
    {
        "text": "Реки с каким названием нет на территории России?",
        "answers": [
            "Спина",
            "Шея",
            "Уста",
            "Палец"
        ],
        "points": 3,
        "difficulty": {
            "__difficulty": 2
        },
        "correct_answer": 0
    },
    {
        "text": "В честь какого растения область Фриули-Венеция-Джулия в Италии ежегодно проводит трёхмесячный фестиваль?",
        "answers": [
            "Спаржа",
            "Лук",
            "Фасоль",
            "Артишок"
        ],
        "points": 3,
        "difficulty": {
            "__difficulty": 2
        },
        "correct_answer": 0
    },
    {
        "text": "В какой из этих столиц бывших союзных республик раньше появилось метро?",
        "answers": [
            "Тбилиси",
            "Минск",
            "Ереван",
            "Баку"
        ],
        "points": 3,
        "difficulty": {
            "__difficulty": 2
        },
        "correct_answer": 0
    },
    {
        "text": "Что используют для поджаривания ломтиков хлеба?",
        "answers": [
            "Тостер",
            "Постер",
            "Винчестер",
            "Компостер"
        ],
        "points": 1,
        "difficulty": {
            "__difficulty": 0
        },
        "correct_answer": 0
    },
    {
        "text": "Какой обитатель водной стихии заслужил репутацию отшельника?",
        "answers": [
            "Рак",
            "Бычок",
            "Дельфин",
            "Медуза"
        ],
        "points": 1,
        "difficulty": {
            "__difficulty": 0
        },
        "correct_answer": 0
    },
    {
        "text": "Какого падежа в русском языке не существует?",
        "answers": [
            "Подложный",
            "Дательный",
            "Творительный",
            "Винительный"
        ],
        "points": 1,
        "difficulty": {
            "__difficulty": 0
        },
        "correct_answer": 0
    },
    {
        "text": "Как называется повесть Астрид Линдгрен: \"Малыш и...\"?",
        "answers": [
            "..Карлсон",
            "..Иван",
            "..собака",
            "..Взрослый"
        ],
        "points": 1,
        "difficulty": {
            "__difficulty": 0
        },
        "correct_answer": 0
    },
    {
        "text": "Что разбудило Спящую Красавицу?",
        "answers": [
            "Поцелуй принца",
            "Шумные соседи",
            "Будильник",
            "Телефон"
        ],
        "points": 1,
        "difficulty": {
            "__difficulty": 0
        },
        "correct_answer": 0
    },
    {
        "text": "Где проходила Олимпиада, на которой бросок А. Белова вывел баскетбольную команду СССР в чемпионы?",
        "answers": [
            "Мюнхен",
            "Рим",
            "Монреаль",
            "Мехико"
        ],
        "points": 2,
        "difficulty": {
            "__difficulty": 1
        },
        "correct_answer": 0
    },
    {
        "text": "Сколько корон на Государственном гербе РФ?",
        "answers": [
            "Три",
            "Одна",
            "Две",
            "Пять"
        ],
        "points": 2,
        "difficulty": {
            "__difficulty": 1
        },
        "correct_answer": 0
    },
    {
        "text": "Месторасположение какой из этих станций в Антарктиде совпадает с полюсом холода?",
        "answers": [
            "\"Восток\"",
            "\"Пионерская\"",
            "\"Молодёжная\"",
            "\"Мирный\""
        ],
        "points": 2,
        "difficulty": {
            "__difficulty": 1
        },
        "correct_answer": 0
    },
    {
        "text": "Какой персонаж оперы Глинки \"Руслан и Людмила\" не поёт?",
        "answers": [
            "Черномор",
            "Ратмир",
            "Наина",
            "Финн"
        ],
        "points": 2,
        "difficulty": {
            "__difficulty": 1
        },
        "correct_answer": 0
    },
    {
        "text": "На территории какой страны был открыт золотоносный район Клондайк?",
        "answers": [
            "Канада",
            "США",
            "Мексика",
            "Венесуэла"
        ],
        "points": 2,
        "difficulty": {
            "__difficulty": 1
        },
        "correct_answer": 0
    },
    {
        "text": "Кто из перечисленных был пажом во времена Екатерины II?",
        "answers": [
            "А.Н. Радищев",
            "Н.М. Карамзин",
            "Д.И. Фонвизин",
            "Г.Р. Державин"
        ],
        "points": 3,
        "difficulty": {
            "__difficulty": 2
        },
        "correct_answer": 0
    },
    {
        "text": "В честь какого растения область Фриули-Венеция-Джулия в Италии ежегодно проводит трёхмесячный фестиваль?",
        "answers": [
            "Спаржа",
            "Лук",
            "Фасоль",
            "Артишок"
        ],
        "points": 3,
        "difficulty": {
            "__difficulty": 2
        },
        "correct_answer": 0
    },
    {
        "text": "В какой из этих столиц бывших союзных республик раньше появилось метро?",
        "answers": [
            "Тбилиси",
            "Минск",
            "Ереван",
            "Баку"
        ],
        "points": 3,
        "difficulty": {
            "__difficulty": 2
        },
        "correct_answer": 0
    },
    {
        "text": "Какой химический элемент назван в честь злого подземного гнома?",
        "answers": [
            "Кобальт",
            "Берилий",
            "Теллур",
            "Гафний"
        ],
        "points": 3,
        "difficulty": {
            "__difficulty": 2
        },
        "correct_answer": 0
    },
    {
        "text": "Реки с каким названием нет на территории России?",
        "answers": [
            "Спина",
            "Шея",
            "Уста",
            "Палец"
        ],
        "points": 3,
        "difficulty": {
            "__difficulty": 2
        },
        "correct_answer": 0
    },
    {
        "text": "Что используют для поджаривания ломтиков хлеба?",
        "answers": [
            "Тостер",
            "Постер",
            "Винчестер",
            "Компостер"
        ],
        "points": 1,
        "difficulty": {
            "__difficulty": 0
        },
        "correct_answer": 0
    },
    {
        "text": "Какого падежа в русском языке не существует?",
        "answers": [
            "Подложный",
            "Дательный",
            "Творительный",
            "Винительный"
        ],
        "points": 1,
        "difficulty": {
            "__difficulty": 0
        },
        "correct_answer": 0
    },
    {
        "text": "Какой обитатель водной стихии заслужил репутацию отшельника?",
        "answers": [
            "Рак",
            "Бычок",
            "Дельфин",
            "Медуза"
        ],
        "points": 1,
        "difficulty": {
            "__difficulty": 0
        },
        "correct_answer": 0
    },
    {
        "text": "Как называется повесть Астрид Линдгрен: \"Малыш и...\"?",
        "answers": [
            "..Карлсон",
            "..Иван",
            "..собака",
            "..Взрослый"
        ],
        "points": 1,
        "difficulty": {
            "__difficulty": 0
        },
        "correct_answer": 0
    },
    {
        "text": "Что разбудило Спящую Красавицу?",
        "answers": [
            "Поцелуй принца",
            "Шумные соседи",
            "Будильник",
            "Телефон"
        ],
        "points": 1,
        "difficulty": {
            "__difficulty": 0
        },
        "correct_answer": 0
    },
    {
        "text": "Сколько корон на Государственном гербе РФ?",
        "answers": [
            "Три",
            "Одна",
            "Две",
            "Пять"
        ],
        "points": 2,
        "difficulty": {
            "__difficulty": 1
        },
        "correct_answer": 0
    },
    {
        "text": "Какой персонаж оперы Глинки \"Руслан и Людмила\" не поёт?",
        "answers": [
            "Черномор",
            "Ратмир",
            "Наина",
            "Финн"
        ],
        "points": 2,
        "difficulty": {
            "__difficulty": 1
        },
        "correct_answer": 0
    },
    {
        "text": "Где проходила Олимпиада, на которой бросок А. Белова вывел баскетбольную команду СССР в чемпионы?",
        "answers": [
            "Мюнхен",
            "Рим",
            "Монреаль",
            "Мехико"
        ],
        "points": 2,
        "difficulty": {
            "__difficulty": 1
        },
        "correct_answer": 0
    },
    {
        "text": "Месторасположение какой из этих станций в Антарктиде совпадает с полюсом холода?",
        "answers": [
            "\"Восток\"",
            "\"Пионерская\"",
            "\"Молодёжная\"",
            "\"Мирный\""
        ],
        "points": 2,
        "difficulty": {
            "__difficulty": 1
        },
        "correct_answer": 0
    },
    {
        "text": "На территории какой страны был открыт золотоносный район Клондайк?",
        "answers": [
            "Канада",
            "США",
            "Мексика",
            "Венесуэла"
        ],
        "points": 2,
        "difficulty": {
            "__difficulty": 1
        },
        "correct_answer": 0
    },
    {
        "text": "Какой химический элемент назван в честь злого подземного гнома?",
        "answers": [
            "Кобальт",
            "Берилий",
            "Теллур",
            "Гафний"
        ],
        "points": 3,
        "difficulty": {
            "__difficulty": 2
        },
        "correct_answer": 0
    },
    {
        "text": "Кто из перечисленных был пажом во времена Екатерины II?",
        "answers": [
            "А.Н. Радищев",
            "Н.М. Карамзин",
            "Д.И. Фонвизин",
            "Г.Р. Державин"
        ],
        "points": 3,
        "difficulty": {
            "__difficulty": 2
        },
        "correct_answer": 0
    },
    {
        "text": "В какой из этих столиц бывших союзных республик раньше появилось метро?",
        "answers": [
            "Тбилиси",
            "Минск",
            "Ереван",
            "Баку"
        ],
        "points": 3,
        "difficulty": {
            "__difficulty": 2
        },
        "correct_answer": 0
    },
    {
        "text": "Реки с каким названием нет на территории России?",
        "answers": [
            "Спина",
            "Шея",
            "Уста",
            "Палец"
        ],
        "points": 3,
        "difficulty": {
            "__difficulty": 2
        },
        "correct_answer": 0
    },
    {
        "text": "В честь какого растения область Фриули-Венеция-Джулия в Италии ежегодно проводит трёхмесячный фестиваль?",
        "answers": [
            "Спаржа",
            "Лук",
            "Фасоль",
            "Артишок"
        ],
        "points": 3,
        "difficulty": {
            "__difficulty": 2
        },
        "correct_answer": 0
    },
    {
        "text": "Какого падежа в русском языке не существует?",
        "answers": [
            "Подложный",
            "Дательный",
            "Творительный",
            "Винительный"
        ],
        "points": 1,
        "difficulty": {
            "__difficulty": 0
        },
        "correct_answer": 0
    },
    {
        "text": "Как называется повесть Астрид Линдгрен: \"Малыш и...\"?",
        "answers": [
            "..Карлсон",
            "..Иван",
            "..собака",
            "..Взрослый"
        ],
        "points": 1,
        "difficulty": {
            "__difficulty": 0
        },
        "correct_answer": 0
    },
    {
        "text": "Какой обитатель водной стихии заслужил репутацию отшельника?",
        "answers": [
            "Рак",
            "Бычок",
            "Дельфин",
            "Медуза"
        ],
        "points": 1,
        "difficulty": {
            "__difficulty": 0
        },
        "correct_answer": 0
    },
    {
        "text": "Что используют для поджаривания ломтиков хлеба?",
        "answers": [
            "Тостер",
            "Постер",
            "Винчестер",
            "Компостер"
        ],
        "points": 1,
        "difficulty": {
            "__difficulty": 0
        },
        "correct_answer": 0
    },
    {
        "text": "Что разбудило Спящую Красавицу?",
        "answers": [
            "Поцелуй принца",
            "Шумные соседи",
            "Будильник",
            "Телефон"
        ],
        "points": 1,
        "difficulty": {
            "__difficulty": 0
        },
        "correct_answer": 0
    },
    {
        "text": "Месторасположение какой из этих станций в Антарктиде совпадает с полюсом холода?",
        "answers": [
            "\"Восток\"",
            "\"Пионерская\"",
            "\"Молодёжная\"",
            "\"Мирный\""
        ],
        "points": 2,
        "difficulty": {
            "__difficulty": 1
        },
        "correct_answer": 0
    },
    {
        "text": "Какой персонаж оперы Глинки \"Руслан и Людмила\" не поёт?",
        "answers": [
            "Черномор",
            "Ратмир",
            "Наина",
            "Финн"
        ],
        "points": 2,
        "difficulty": {
            "__difficulty": 1
        },
        "correct_answer": 0
    },
    {
        "text": "На территории какой страны был открыт золотоносный район Клондайк?",
        "answers": [
            "Канада",
            "США",
            "Мексика",
            "Венесуэла"
        ],
        "points": 2,
        "difficulty": {
            "__difficulty": 1
        },
        "correct_answer": 0
    },
    {
        "text": "Сколько корон на Государственном гербе РФ?",
        "answers": [
            "Три",
            "Одна",
            "Две",
            "Пять"
        ],
        "points": 2,
        "difficulty": {
            "__difficulty": 1
        },
        "correct_answer": 0
    },
    {
        "text": "Где проходила Олимпиада, на которой бросок А. Белова вывел баскетбольную команду СССР в чемпионы?",
        "answers": [
            "Мюнхен",
            "Рим",
            "Монреаль",
            "Мехико"
        ],
        "points": 2,
        "difficulty": {
            "__difficulty": 1
        },
        "correct_answer": 0
    },
    {
        "text": "В честь какого растения область Фриули-Венеция-Джулия в Италии ежегодно проводит трёхмесячный фестиваль?",
        "answers": [
            "Спаржа",
            "Лук",
            "Фасоль",
            "Артишок"
        ],
        "points": 3,
        "difficulty": {
            "__difficulty": 2
        },
        "correct_answer": 0
    },
    {
        "text": "Реки с каким названием нет на территории России?",
        "answers": [
            "Спина",
            "Шея",
            "Уста",
            "Палец"
        ],
        "points": 3,
        "difficulty": {
            "__difficulty": 2
        },
        "correct_answer": 0
    },
    {
        "text": "Кто из перечисленных был пажом во времена Екатерины II?",
        "answers": [
            "А.Н. Радищев",
            "Н.М. Карамзин",
            "Д.И. Фонвизин",
            "Г.Р. Державин"
        ],
        "points": 3,
        "difficulty": {
            "__difficulty": 2
        },
        "correct_answer": 0
    },
    {
        "text": "В какой из этих столиц бывших союзных республик раньше появилось метро?",
        "answers": [
            "Тбилиси",
            "Минск",
            "Ереван",
            "Баку"
        ],
        "points": 3,
        "difficulty": {
            "__difficulty": 2
        },
        "correct_answer": 0
    },
    {
        "text": "Какой химический элемент назван в честь злого подземного гнома?",
        "answers": [
            "Кобальт",
            "Берилий",
            "Теллур",
            "Гафний"
        ],
        "points": 3,
        "difficulty": {
            "__difficulty": 2
        },
        "correct_answer": 0
    }
]